{
  "schema": "primeproject.ticket120-twin-low-divisor-pair-savings-audit.v1",
  "generated_at": "2026-07-15T04:30:00+09:00",
  "problem_id": "goldbach",
  "ticket_id": "GB-TICKET-120",
  "status": "problem_specific_target_preserved_open",
  "route": "JointBalancedGoldbachPreserved",
  "proof_or_counterexample_mode": "preserve the independent target during the Twin low-divisor structural audit",
  "attempt": "No Twin Gram or low-divisor saving result is transferred to this problem.",
  "bounded_result": {
    "source_ticket": "GB-TICKET-119",
    "independent_target": "JointBalancedVaughanGoldbachResidualEnvelope"
  },
  "obstruction": "TICKET120 supplies no new problem-specific infinite theorem here.",
  "candidate_theorem": "JointBalancedVaughanGoldbachResidualEnvelope",
  "next_experiment": "Continue JointBalancedVaughanGoldbachResidualEnvelope with its own proof and counterexample oracle.",
  "claim_boundary": "No goldbach proof and no certified goldbach counterexample."
}
