{
  "schema": "primeproject.ticket135-conditional-bridges-and-exceptional-set.v1",
  "generated_at": "2026-07-21T01:15:00+09:00",
  "problem_id": "collatz",
  "ticket_id": "CO-TICKET-135",
  "status": "exact_conditional_bridge_or_no_go_conjecture_open",
  "route": "MinimalNegativeSlopePrefixesFormFullMeasurePrefixFreeCover",
  "bounded_result": {
    "audit_ref": "collatz"
  },
  "candidate_theorem": "NaturalCodesCrossAffineDescentThreshold",
  "next_experiment": "Characterize the null exceptional code set and prove that every natural valuation code leaves it while exceeding its affine descent threshold.",
  "claim_boundary": "No conjecture proof and no certified conjecture counterexample.",
  "proof_boundary": "The natural positive odd integers form a countable dense Haar-null set, so they could lie inside the exceptional null set. Moreover a slope below one does not by itself beat the positive affine term for a given integer. This theorem is not a pointwise Collatz descent proof."
}
