{
  "problem_id": "riemann",
  "ticket_id": "RH-TICKET-38",
  "status": "proof_pressure_open",
  "route": "SymbolicZeroExclusionExtension",
  "proof_or_counterexample_mode": "symbolic_pointwise_extension_transfer",
  "attempt": "Transfer Ticket 38's lesson: a bounded pointwise-looking rank still needs a symbolic extension theorem. Simple averaged or scalar potentials must be stress-tested against explicit exceptional objects.",
  "bounded_result": {
    "source_ticket": "RH-TICKET-37",
    "source_route": "PointwiseZeroExclusionRank",
    "discarded_extension": "finite-height or averaged zero pressure as a pointwise zero-exclusion proof",
    "retained_extension": "kernel/state positivity that rejects every off-critical zero configuration"
  },
  "obstruction": "The proof gap is not finite evidence; it is the missing symbolic extension from bounded-compatible rank pressure to every possible exceptional object.",
  "candidate_theorem": "Every hypothetical off-critical zero induces a finite symbolic obstruction in a positive kernel certificate.",
  "next_experiment": "Build a zero-configuration graph and search for nonnegative kernel potentials with no exceptional cycles.",
  "claim_boundary": "No riemann proof and no certified riemann counterexample."
}
